ninja_jwt/__init__.py
ninja_jwt/authentication.py
ninja_jwt/backends.py
ninja_jwt/compat.py
ninja_jwt/controller.py
ninja_jwt/exceptions.py
ninja_jwt/models.py
ninja_jwt/py.typed
ninja_jwt/schema.py
ninja_jwt/schema_control.py
ninja_jwt/settings.py
ninja_jwt/state.py
ninja_jwt/tokens.py
ninja_jwt/utils.py
ninja_jwt/locale/cs/LC_MESSAGES/django.mo
ninja_jwt/locale/cs/LC_MESSAGES/django.po
ninja_jwt/locale/de_CH/LC_MESSAGES/django.mo
ninja_jwt/locale/de_CH/LC_MESSAGES/django.po
ninja_jwt/locale/es/LC_MESSAGES/django.mo
ninja_jwt/locale/es/LC_MESSAGES/django.po
ninja_jwt/locale/es_AR/LC_MESSAGES/django.mo
ninja_jwt/locale/es_AR/LC_MESSAGES/django.po
ninja_jwt/locale/es_CL/LC_MESSAGES/django.mo
ninja_jwt/locale/es_CL/LC_MESSAGES/django.po
ninja_jwt/locale/fa_IR/LC_MESSAGES/django.mo
ninja_jwt/locale/fa_IR/LC_MESSAGES/django.po
ninja_jwt/locale/fr/LC_MESSAGES/django.mo
ninja_jwt/locale/fr/LC_MESSAGES/django.po
ninja_jwt/locale/id_ID/LC_MESSAGES/django.mo
ninja_jwt/locale/id_ID/LC_MESSAGES/django.po
ninja_jwt/locale/it_IT/LC_MESSAGES/django.mo
ninja_jwt/locale/it_IT/LC_MESSAGES/django.po
ninja_jwt/locale/ko_KR/LC_MESSAGES/django.mo
ninja_jwt/locale/ko_KR/LC_MESSAGES/django.po
ninja_jwt/locale/nl_NL/LC_MESSAGES/django.mo
ninja_jwt/locale/nl_NL/LC_MESSAGES/django.po
ninja_jwt/locale/pl_PL/LC_MESSAGES/django.mo
ninja_jwt/locale/pl_PL/LC_MESSAGES/django.po
ninja_jwt/locale/pt_BR/LC_MESSAGES/django.mo
ninja_jwt/locale/pt_BR/LC_MESSAGES/django.po
ninja_jwt/locale/ro/LC_MESSAGES/django.mo
ninja_jwt/locale/ro/LC_MESSAGES/django.po
ninja_jwt/locale/ru_RU/LC_MESSAGES/django.mo
ninja_jwt/locale/ru_RU/LC_MESSAGES/django.po
ninja_jwt/locale/sv/LC_MESSAGES/django.mo
ninja_jwt/locale/sv/LC_MESSAGES/django.po
ninja_jwt/locale/tr/LC_MESSAGES/django.mo
ninja_jwt/locale/tr/LC_MESSAGES/django.po
ninja_jwt/locale/uk_UA/LC_MESSAGES/django.mo
ninja_jwt/locale/uk_UA/LC_MESSAGES/django.po
ninja_jwt/locale/zh_Hans/LC_MESSAGES/django.mo
ninja_jwt/locale/zh_Hans/LC_MESSAGES/django.po
django_ninja_jwt-5.4.3.dist-info/licenses/LICENSE.txt
django_ninja_jwt-5.4.3.dist-info/WHEEL
django_ninja_jwt-5.4.3.dist-info/METADATA
django_ninja_jwt-5.4.3.dist-info/RECORD
