Metadata-Version: 2.4
Name: django-ninja-jwt
Version: 5.4.3
Summary: Django Ninja JWT - JSON Web Token for Django-Ninja
Author-email: Ezeudoh Tochukwu <tochukwu.ezeudoh@gmail.com>
Requires-Python: >=3.7
Classifier: Intended Audience :: Information Technology
Classifier: Intended Audience :: System Administrators
Classifier: Operating System :: OS Independent
Classifier: Topic :: Internet
Classifier: Topic :: Software Development :: Libraries :: Application Frameworks
Classifier: Topic :: Software Development :: Libraries :: Python Modules
Classifier: Topic :: Software Development :: Libraries
Classifier: Topic :: Software Development
Classifier: Typing :: Typed
Classifier: Environment :: Web Environment
Classifier: Intended Audience :: Developers
Classifier: License :: OSI Approved :: MIT License
Classifier: Programming Language :: Python :: 3
Classifier: Programming Language :: Python :: 3.7
Classifier: Programming Language :: Python :: 3.8
Classifier: Programming Language :: Python :: 3.9
Classifier: Programming Language :: Python :: 3.10
Classifier: Programming Language :: Python :: 3.11
Classifier: Programming Language :: Python :: 3.12
Classifier: Programming Language :: Python :: 3 :: Only
Classifier: Framework :: Django
Classifier: Framework :: Django :: 3.1
Classifier: Framework :: Django :: 3.2
Classifier: Framework :: Django :: 4.0
Classifier: Framework :: Django :: 4.1
Classifier: Framework :: AsyncIO
Classifier: Topic :: Internet :: WWW/HTTP :: HTTP Servers
Classifier: Topic :: Internet :: WWW/HTTP
License-File: LICENSE.txt
Requires-Dist: Django >= 2.1
Requires-Dist: pyjwt>=1.7.1,<3
Requires-Dist: pyjwt[crypto]
Requires-Dist: pydantic-settings>=2.0.0
Requires-Dist: django-ninja-extra >= 0.30.5
Requires-Dist: cryptography>=3.3.1 ; extra == "crypto"
Project-URL: Documentation, https://github.com/eadwinCode/django-ninja-jwt
Project-URL: Source, https://github.com/eadwinCode/django-ninja-jwt
Provides-Extra: crypto
